laskea/__init__.py
laskea/__main__.py
laskea/cli.py
laskea/config.py
laskea/embed.py
laskea/env.py
laskea/laskea.py
laskea/transform.py
laskea/api/__init__.py
laskea/api/excel.py
laskea/api/jira.py
laskea/api/tabulator.py
laskea-2023.12.4.dist-info/LICENSE
laskea-2023.12.4.dist-info/METADATA
laskea-2023.12.4.dist-info/WHEEL
laskea-2023.12.4.dist-info/entry_points.txt
laskea-2023.12.4.dist-info/top_level.txt
laskea-2023.12.4.dist-info/RECORD
