Metadata-Version: 2.1
Name: laskea
Version: 2023.12.4
Summary: Calculate (Finnish: laskea) some parts.
Author-email: Stefan Hagen <stefan@hagen.link>
Maintainer-email: Stefan Hagen <stefan@hagen.link>
Project-URL: Homepage, https://git.sr.ht/~sthagen/laskea
Project-URL: Bug-Tracker, https://todo.sr.ht/~sthagen/laskea
Project-URL: Documentation, https://codes.dilettant.life/docs/laskea
Project-URL: Source-Code, https://git.sr.ht/~sthagen/laskea
Project-URL: Test-Coverage, https://codes.dilettant.life/coverage/laskea
Keywords: code-generation,developer-tools,markdown,validation,erification
Classifier: Development Status :: 5 - Production/Stable
Classifier: Intended Audience :: Developers
Classifier: License :: OSI Approved :: MIT License
Classifier: Programming Language :: Python :: 3.10
Classifier: Programming Language :: Python :: 3.11
Classifier: Programming Language :: Python :: 3.12
Classifier: Programming Language :: Python :: 3.9
Requires-Python: >=3.9
License-File: LICENSE
Requires-Dist: atlassian-python-api >=3.41.3
Requires-Dist: cogapp >=3.3.0
Requires-Dist: defusedxml >=0.7.1
Requires-Dist: jmespath >=1.0.1
Requires-Dist: openpyxl >=3.1.2
Requires-Dist: pydantic >=2.5.1
Requires-Dist: requests-cache >=1.1.0
Requires-Dist: scooby >=0.9.2
Requires-Dist: typer >=0.9.0
Provides-Extra: dev
Requires-Dist: black ; extra == 'dev'
Requires-Dist: coverage ; extra == 'dev'
Requires-Dist: hypothesis ; extra == 'dev'
Requires-Dist: mypy ; extra == 'dev'
Requires-Dist: pytest ; extra == 'dev'
Requires-Dist: pytest-cov ; extra == 'dev'
Requires-Dist: pytest-flake8 ; extra == 'dev'
Requires-Dist: ruff ; extra == 'dev'
Requires-Dist: types-jmespath ; extra == 'dev'
